ezhash/__init__.py
ezhash/main.py
ezhash-1.0.0.dist-info/entry_points.txt
ezhash-1.0.0.dist-info/LICENSE
ezhash-1.0.0.dist-info/WHEEL
ezhash-1.0.0.dist-info/METADATA
ezhash-1.0.0.dist-info/RECORD
