Metadata-Version: 2.1
Name: ezhash
Version: 1.0.0
Summary: CLI tool which computes and compares file hash.
License: MIT
Author: Naffah Abdulla Rasheed
Author-email: mail@naffah.me
Requires-Python: >=3.9,<4.0
Classifier: License :: OSI Approved :: MIT License
Classifier: Programming Language :: Python :: 3
Classifier: Programming Language :: Python :: 3.10
Classifier: Programming Language :: Python :: 3.9
Requires-Dist: tqdm (>=4.62.3,<5.0.0)
Requires-Dist: typer[all] (>=0.4.0,<0.5.0)
